brainstorm_search/__init__.py
brainstorm_search/helper.py
brainstorm_search/main.py
brainstorm_search-0.0.1.dist-info/LICENSE
brainstorm_search-0.0.1.dist-info/METADATA
brainstorm_search-0.0.1.dist-info/WHEEL
brainstorm_search-0.0.1.dist-info/entry_points.txt
brainstorm_search-0.0.1.dist-info/top_level.txt
brainstorm_search-0.0.1.dist-info/RECORD
