Metadata-Version: 2.1
Name: brainstorm-search
Version: 0.0.1
Summary: Summarize idea lists from Duckduckgo. Make idea brainstorming efficient.
Home-page: https://github.com/jnbli/brainstorm-search
Author: Jonathan Li
License: MIT License
Project-URL: Bug Tracker, https://github.com/jnbli/brainstorm-search/issues
Platform: UNKNOWN
Requires-Python: >=3.6
Requires-Dist: setuptools (>=42)
Requires-Dist: wheel
Requires-Dist: beautifulsoup4
Requires-Dist: duckduckgo-search
